examples/__init__.py
examples/configs_examples/__init__.py
examples/configs_examples/alexnet_flowers17.py
examples/configs_examples/autoencoder.py
examples/configs_examples/conv_autoencoder.py
examples/configs_examples/conv_mnist.py
examples/configs_examples/convnet_cifar10.py
examples/configs_examples/denoising_conv_autoencoder.py
examples/configs_examples/lenet.py
examples/configs_examples/variational_autoencoder.py
examples/configs_examples/vgg19.py
examples/programatic_examples/__init__.py
examples/programatic_examples/alexnet_flowers17.py
examples/programatic_examples/autoencoder.py
examples/programatic_examples/boston.py
examples/programatic_examples/conv_autoencoder.py
examples/programatic_examples/conv_mnist.py
examples/programatic_examples/convnet_cifar10.py
examples/programatic_examples/denoising_conv_autoencoder.py
examples/programatic_examples/distributed_example.py
examples/programatic_examples/imdb_sentiment_bidirectional_lsmt.py
examples/programatic_examples/imdb_sentiment_lstm.py
examples/programatic_examples/lenet.py
examples/programatic_examples/timeseries.py
examples/programatic_examples/variational_autoencoder.py
examples/programatic_examples/variational_autoencoder_mnist.py
examples/programatic_examples/vgg19.py
examples/programatic_examples/xor.py
examples/reinforcement_learning_examples/__init__.py
examples/reinforcement_learning_examples/dqn_cartpole.py
examples/reinforcement_learning_examples/dueling_ddqn_cartpole.py
examples/reinforcement_learning_examples/naf_pendulum.py
examples/reinforcement_learning_examples/trpo_cartpole.py
examples/reinforcement_learning_examples/vpg_cartpole.py
polyaxon_lib/__init__.py
polyaxon_lib/activations.py
polyaxon_lib/constraints.py
polyaxon_lib/initializations.py
polyaxon_lib/losses.py
polyaxon_lib/metrics.py
polyaxon_lib/modes.py
polyaxon_lib/optimizers.py
polyaxon_lib/regularizations.py
polyaxon_lib/variables.py
polyaxon_lib/bridges/__init__.py
polyaxon_lib-0.0.4.dist-info/DESCRIPTION.rst
polyaxon_lib-0.0.4.dist-info/METADATA
polyaxon_lib-0.0.4.dist-info/RECORD
polyaxon_lib-0.0.4.dist-info/WHEEL
polyaxon_lib-0.0.4.dist-info/metadata.json
polyaxon_lib-0.0.4.dist-info/top_level.txt
