Metadata-Version: 2.0
Name: polyaxon-lib
Version: 0.0.4
Summary: Deep Learning library for TensorFlow for building end to end models and experiments.
Home-page: https://github.com/polyaxon/polyaxon-lib
Author: Mourad Mourafiq
Author-email: mouradmourafiq@gmail.com
License: MIT
Keywords: polyaxon,tensorFlow,deep-learning,machine-learning,data-science,neural-networks,artificial-intelligence,ai,reinforcement-learning,kubernetes
Platform: any
Classifier: Programming Language :: Python
Classifier: Operating System :: OS Independent
Classifier: Intended Audience :: Developers
Classifier: Intended Audience :: Science/Research
Classifier: Topic :: Scientific/Engineering :: Artificial Intelligence
Requires-Dist: numpy (==1.13.1)
Requires-Dist: Pillow (==4.2.1)
Requires-Dist: polyaxon-schemas (==0.0.4)
Requires-Dist: polyaxon-helper (==0.0.4)
Requires-Dist: six (==1.11.0)
Requires-Dist: tensorflow (>=1.3.0)
